README.txt
setup.py
Products/__init__.py
Products.PermissionComprehensible.egg-info/PKG-INFO
Products.PermissionComprehensible.egg-info/SOURCES.txt
Products.PermissionComprehensible.egg-info/dependency_links.txt
Products.PermissionComprehensible.egg-info/entry_points.txt
Products.PermissionComprehensible.egg-info/namespace_packages.txt
Products.PermissionComprehensible.egg-info/not-zip-safe
Products.PermissionComprehensible.egg-info/requires.txt
Products.PermissionComprehensible.egg-info/top_level.txt
Products/PermissionComprehensible/__init__.py
Products/PermissionComprehensible/changes.txt
Products/PermissionComprehensible/configure.zcml
Products/PermissionComprehensible/permissioncomprehensible.pt
Products/PermissionComprehensible/permissioncomprehensible.py
Products/PermissionComprehensible/permissions_for_role_hack.py
Products/PermissionComprehensible/readme.txt
Products/PermissionComprehensible/skins.zcml
Products/PermissionComprehensible/version.txt
Products/PermissionComprehensible/_darcs/index_invalid
Products/PermissionComprehensible/_darcs/inventory
Products/PermissionComprehensible/_darcs/tentative_pristine
Products/PermissionComprehensible/_darcs/patches/20100321151944-422b6-63fe1975f43187e93269c15abc98264b2df7fe4d.gz
Products/PermissionComprehensible/_darcs/patches/20100321211525-422b6-b1f746b35f2c4d80b0c630b9c2b1ad015dd6bbfb.gz
Products/PermissionComprehensible/_darcs/patches/20120130124652-422b6-1455eb6cb1ce6885b0b8aa6878ceed33460113ca.gz
Products/PermissionComprehensible/_darcs/patches/pending
Products/PermissionComprehensible/_darcs/patches/pending.tentative
Products/PermissionComprehensible/_darcs/prefs/author
Products/PermissionComprehensible/_darcs/prefs/binaries
Products/PermissionComprehensible/_darcs/prefs/boring
Products/PermissionComprehensible/_darcs/prefs/defaultrepo
Products/PermissionComprehensible/_darcs/prefs/motd
Products/PermissionComprehensible/_darcs/prefs/repos
Products/PermissionComprehensible/_darcs/pristine/__init__.py
Products/PermissionComprehensible/_darcs/pristine/changes.txt
Products/PermissionComprehensible/_darcs/pristine/configure.zcml
Products/PermissionComprehensible/_darcs/pristine/permissioncomprehensible.pt
Products/PermissionComprehensible/_darcs/pristine/permissioncomprehensible.py
Products/PermissionComprehensible/_darcs/pristine/permissions_for_role_hack.py
Products/PermissionComprehensible/_darcs/pristine/readme.txt
